ficto/__init__.py
ficto/main.py
ficto/core/__init__.py
ficto/core/generate.py
ficto/helper/__init__.py
ficto/helper/builder.py
ficto/helper/data_module.py
ficto-0.0.8.dist-info/LICENSE
ficto-0.0.8.dist-info/METADATA
ficto-0.0.8.dist-info/WHEEL
ficto-0.0.8.dist-info/entry_points.txt
ficto-0.0.8.dist-info/top_level.txt
ficto-0.0.8.dist-info/RECORD
